LICENSE
README.md
weevils_django/__init__.py
weevils_django/oauth.py
weevils_django-0.0.1a0.dist-info/LICENSE
weevils_django-0.0.1a0.dist-info/METADATA
weevils_django-0.0.1a0.dist-info/WHEEL
weevils_django-0.0.1a0.dist-info/RECORD
