Metadata-Version: 2.1
Name: weevils-django
Version: 0.0.1a0
Summary: 
Home-page: https://docs.weevils.io/api-client
License: MIT
Author: weevils.io
Author-email: code@weevils.io
Requires-Python: >=3.8,<4.0
Classifier: Development Status :: 2 - Pre-Alpha
Classifier: License :: OSI Approved :: MIT License
Classifier: Programming Language :: Python :: 3
Classifier: Programming Language :: Python :: 3.8
Classifier: Programming Language :: Python :: 3.9
Classifier: Programming Language :: Python :: 3.10
Classifier: Programming Language :: Python :: 3.11
Classifier: Programming Language :: Python :: 3.10
Classifier: Programming Language :: Python :: 3.11
Classifier: Programming Language :: Python :: 3.8
Classifier: Programming Language :: Python :: 3.9
Requires-Dist: django (>=4.1.7,<5.0.0)
Requires-Dist: social-auth-app-django (>=5.1.0,<6.0.0)
